{
"meta":{"test_sets":[],"test_metrics":[],"learn_metrics":[{"best_value":"Min","name":"Logloss"}],"launch_mode":"Train","parameters":"","iteration_count":100,"learn_sets":["learn"],"name":"experiment"},
"iterations":[
{"learn":[0.3579940787],"iteration":0,"passed_time":0.0774408582,"remaining_time":7.666644962},
{"learn":[0.2655885688],"iteration":1,"passed_time":0.1521130866,"remaining_time":7.453541243},
{"learn":[0.214859271],"iteration":2,"passed_time":0.2155007861,"remaining_time":6.967858752},
{"learn":[0.1924493859],"iteration":3,"passed_time":0.2703329423,"remaining_time":6.487990615},
{"learn":[0.1819401954],"iteration":4,"passed_time":0.3360124562,"remaining_time":6.384236669},
{"learn":[0.1699434836],"iteration":5,"passed_time":0.3995922012,"remaining_time":6.260277819},
{"learn":[0.1632104818],"iteration":6,"passed_time":0.4684336441,"remaining_time":6.223475558},
{"learn":[0.1574021388],"iteration":7,"passed_time":0.5326678891,"remaining_time":6.125680725},
{"learn":[0.1555396266],"iteration":8,"passed_time":0.592244808,"remaining_time":5.988253059},
{"learn":[0.1532481852],"iteration":9,"passed_time":0.6540925862,"remaining_time":5.886833275},
{"learn":[0.1508899061],"iteration":10,"passed_time":0.7130994821,"remaining_time":5.769623083},
{"learn":[0.1474065398],"iteration":11,"passed_time":0.7815491613,"remaining_time":5.731360516},
{"learn":[0.1403141684],"iteration":12,"passed_time":0.8439231335,"remaining_time":5.647793278},
{"learn":[0.1387427356],"iteration":13,"passed_time":0.8980916668,"remaining_time":5.51684881},
{"learn":[0.13560711],"iteration":14,"passed_time":0.9514255017,"remaining_time":5.391411176},
{"learn":[0.1333715881],"iteration":15,"passed_time":1.015175095,"remaining_time":5.32966925},
{"learn":[0.1319376319],"iteration":16,"passed_time":1.069442205,"remaining_time":5.221394293},
{"learn":[0.129676393],"iteration":17,"passed_time":1.155034715,"remaining_time":5.261824811},
{"learn":[0.1256143634],"iteration":18,"passed_time":1.239287514,"remaining_time":5.283278349},
{"learn":[0.1242449158],"iteration":19,"passed_time":1.315482355,"remaining_time":5.261929419},
{"learn":[0.1231622474],"iteration":20,"passed_time":1.393708424,"remaining_time":5.242998357},
{"learn":[0.1210016571],"iteration":21,"passed_time":1.483458829,"remaining_time":5.259535849},
{"learn":[0.1198435874],"iteration":22,"passed_time":1.555902316,"remaining_time":5.208890362},
{"learn":[0.1170149798],"iteration":23,"passed_time":1.701422858,"remaining_time":5.387839049},
{"learn":[0.1148574888],"iteration":24,"passed_time":1.781346078,"remaining_time":5.344038235},
{"learn":[0.1134539255],"iteration":25,"passed_time":1.86760283,"remaining_time":5.315484978},
{"learn":[0.1127993344],"iteration":26,"passed_time":1.931107165,"remaining_time":5.221141594},
{"learn":[0.1113737983],"iteration":27,"passed_time":2.000847325,"remaining_time":5.145035978},
{"learn":[0.1097931962],"iteration":28,"passed_time":2.129719574,"remaining_time":5.214141026},
{"learn":[0.1077473287],"iteration":29,"passed_time":2.266671055,"remaining_time":5.288899129},
{"learn":[0.1061580873],"iteration":30,"passed_time":2.419137841,"remaining_time":5.384532614},
{"learn":[0.1053007608],"iteration":31,"passed_time":2.524686689,"remaining_time":5.364959215},
{"learn":[0.1045609105],"iteration":32,"passed_time":2.634563102,"remaining_time":5.34896145},
{"learn":[0.1040806115],"iteration":33,"passed_time":2.762970472,"remaining_time":5.363413269},
{"learn":[0.1034348936],"iteration":34,"passed_time":2.916798963,"remaining_time":5.416912359},
{"learn":[0.1019286711],"iteration":35,"passed_time":2.991022039,"remaining_time":5.317372513},
{"learn":[0.100814029],"iteration":36,"passed_time":3.048299884,"remaining_time":5.190348452},
{"learn":[0.1004270758],"iteration":37,"passed_time":3.103094352,"remaining_time":5.062943417},
{"learn":[0.09983494862],"iteration":38,"passed_time":3.165119656,"remaining_time":4.95057177},
{"learn":[0.09946019519],"iteration":39,"passed_time":3.223083066,"remaining_time":4.834624599},
{"learn":[0.09868975472],"iteration":40,"passed_time":3.32641245,"remaining_time":4.786788648},
{"learn":[0.09833505358],"iteration":41,"passed_time":3.378305848,"remaining_time":4.665279504},
{"learn":[0.09749540487],"iteration":42,"passed_time":3.426712003,"remaining_time":4.542385678},
{"learn":[0.09726063119],"iteration":43,"passed_time":3.476579619,"remaining_time":4.424737697},
{"learn":[0.09686548029],"iteration":44,"passed_time":3.533905758,"remaining_time":4.319218148},
{"learn":[0.09639426031],"iteration":45,"passed_time":3.601620758,"remaining_time":4.227989585},
{"learn":[0.09597130351],"iteration":46,"passed_time":3.668465432,"remaining_time":4.136780168},
{"learn":[0.09562202335],"iteration":47,"passed_time":3.718326492,"remaining_time":4.028187033},
{"learn":[0.09530619914],"iteration":48,"passed_time":3.769527638,"remaining_time":3.923385909},
{"learn":[0.09477070422],"iteration":49,"passed_time":3.816437133,"remaining_time":3.816437133},
{"learn":[0.09411334807],"iteration":50,"passed_time":3.933460737,"remaining_time":3.779207374},
{"learn":[0.09370782266],"iteration":51,"passed_time":4.097580649,"remaining_time":3.782382137},
{"learn":[0.09349017375],"iteration":52,"passed_time":4.267850242,"remaining_time":3.784697384},
{"learn":[0.09284230345],"iteration":53,"passed_time":4.335640766,"remaining_time":3.693323616},
{"learn":[0.09204092457],"iteration":54,"passed_time":4.391661276,"remaining_time":3.593177408},
{"learn":[0.09157927911],"iteration":55,"passed_time":4.445218344,"remaining_time":3.492671556},
{"learn":[0.09140098671],"iteration":56,"passed_time":4.49604968,"remaining_time":3.391756776},
{"learn":[0.09101747931],"iteration":57,"passed_time":4.56338552,"remaining_time":3.304520549},
{"learn":[0.09079458921],"iteration":58,"passed_time":4.650370911,"remaining_time":3.231613684},
{"learn":[0.09043477421],"iteration":59,"passed_time":4.755927786,"remaining_time":3.170618524},
{"learn":[0.09036165363],"iteration":60,"passed_time":4.836219393,"remaining_time":3.09200912},
{"learn":[0.08989344288],"iteration":61,"passed_time":4.914541942,"remaining_time":3.01213861},
{"learn":[0.08959977041],"iteration":62,"passed_time":4.962987969,"remaining_time":2.914770712},
{"learn":[0.08941251772],"iteration":63,"passed_time":5.015432972,"remaining_time":2.821181047},
{"learn":[0.08925787834],"iteration":64,"passed_time":5.071451574,"remaining_time":2.730781617},
{"learn":[0.08890106775],"iteration":65,"passed_time":5.121811009,"remaining_time":2.638508702},
{"learn":[0.08855381606],"iteration":66,"passed_time":5.162549469,"remaining_time":2.542748246},
{"learn":[0.08829737948],"iteration":67,"passed_time":5.206476873,"remaining_time":2.450106764},
{"learn":[0.08783834965],"iteration":68,"passed_time":5.31491057,"remaining_time":2.387858372},
{"learn":[0.08745398568],"iteration":69,"passed_time":5.482596246,"remaining_time":2.349684105},
{"learn":[0.08723454151],"iteration":70,"passed_time":5.570391355,"remaining_time":2.275230272},
{"learn":[0.08716251883],"iteration":71,"passed_time":5.656969237,"remaining_time":2.199932481},
{"learn":[0.08699497176],"iteration":72,"passed_time":5.731460244,"remaining_time":2.119855159},
{"learn":[0.08683389124],"iteration":73,"passed_time":5.801400753,"remaining_time":2.038329994},
{"learn":[0.08665392471],"iteration":74,"passed_time":5.859685465,"remaining_time":1.953228488},
{"learn":[0.08598054291],"iteration":75,"passed_time":5.918283882,"remaining_time":1.868931752},
{"learn":[0.08583315475],"iteration":76,"passed_time":5.977658017,"remaining_time":1.785534213},
{"learn":[0.08565509881],"iteration":77,"passed_time":6.056955887,"remaining_time":1.708372173},
{"learn":[0.08543799099],"iteration":78,"passed_time":6.145980137,"remaining_time":1.633741556},
{"learn":[0.08526354541],"iteration":79,"passed_time":6.207468769,"remaining_time":1.551867192},
{"learn":[0.08513864034],"iteration":80,"passed_time":6.264269184,"remaining_time":1.469396475},
{"learn":[0.08496424517],"iteration":81,"passed_time":6.324852974,"remaining_time":1.38838236},
{"learn":[0.08483654906],"iteration":82,"passed_time":6.388391239,"remaining_time":1.308465675},
{"learn":[0.0847033458],"iteration":83,"passed_time":6.451244093,"remaining_time":1.228808399},
{"learn":[0.08455241701],"iteration":84,"passed_time":6.509556964,"remaining_time":1.148745347},
{"learn":[0.08440411057],"iteration":85,"passed_time":6.558364685,"remaining_time":1.067640763},
{"learn":[0.08402845842],"iteration":86,"passed_time":6.609121847,"remaining_time":0.9875699311},
{"learn":[0.08381097812],"iteration":87,"passed_time":6.661582525,"remaining_time":0.9083976171},
{"learn":[0.08366473834],"iteration":88,"passed_time":6.708666657,"remaining_time":0.8291610475},
{"learn":[0.08334112283],"iteration":89,"passed_time":6.761924495,"remaining_time":0.7513249439},
{"learn":[0.08311723363],"iteration":90,"passed_time":6.805186023,"remaining_time":0.6730403759},
{"learn":[0.08302342205],"iteration":91,"passed_time":6.846558558,"remaining_time":0.5953529181},
{"learn":[0.08294053956],"iteration":92,"passed_time":6.882504155,"remaining_time":0.5180379472},
{"learn":[0.08286216005],"iteration":93,"passed_time":6.917945422,"remaining_time":0.4415709844},
{"learn":[0.0826287712],"iteration":94,"passed_time":6.954695154,"remaining_time":0.366036587},
{"learn":[0.08251764126],"iteration":95,"passed_time":6.988791395,"remaining_time":0.2911996415},
{"learn":[0.08243536175],"iteration":96,"passed_time":7.029425871,"remaining_time":0.2174049239},
{"learn":[0.08233340359],"iteration":97,"passed_time":7.067254709,"remaining_time":0.1442296879},
{"learn":[0.08208420667],"iteration":98,"passed_time":7.103684817,"remaining_time":0.0717543921},
{"learn":[0.08179278525],"iteration":99,"passed_time":7.141734171,"remaining_time":0}
]}